{"indexed":{"date-parts":[[2018,6,6]],"date-time":"2018-06-06T18:42:34Z","timestamp":1528310554836},"reference-count":22,"publisher":"Cambridge University Press (CUP)","issue":"11","content-domain":{"domain":[],"crossmark-restriction":false},"published-print":{"date-parts":[[2011,11]]},"DOI":"10.1017\/s0022215111001691","type":"article-journal","created":{"date-parts":[[2011,8,16]],"date-time":"2011-08-16T12:35:44Z","timestamp":1313498144000},"page":"1109-1115","source":"Crossref","is-referenced-by-count":12,"title":"Spectrum of radiological appearances of necrotising external otitis: a pictorial review","prefix":"10.1017","volume":"125","author":[{"given":"P","family":"Mehrotra","sequence":"first","affiliation":[]},{"given":"M R","family":"Elbadawey","sequence":"additional","affiliation":[]},{"given":"I","family":"Zammit-Maempel","sequence":"additional","affiliation":[]}],"member":"56","published-online":{"date-parts":[[2011,8,16]]},"reference":[{"key":"S0022215111001691_ref19","author":"Amorosa","volume":"521","first-page":"3","year":"1996","journal-title":"Acta Otolaryngol Suppl","DOI":"10.3109\/00016489609137954x","doi-asserted-by":"crossref"},{"key":"S0022215111001691_ref20","DOI":"10.1258\/0022215053222978","doi-asserted-by":"publisher"},{"key":"S0022215111001691_ref17","author":"Sreepada","volume":"11","first-page":"391","year":"2003","journal-title":"Curr Opin Otolaryngol Head Neck Surg","DOI":"10.1097\/00020840-200310000-00002","doi-asserted-by":"crossref"},{"key":"S0022215111001691_ref16","author":"Grandis","volume":"196","first-page":"499","year":"1995","journal-title":"Radiology","DOI":"10.1148\/radiology.196.2.7617867","doi-asserted-by":"crossref"},{"key":"S0022215111001691_ref15","author":"Bhandary","volume":"9","first-page":"64","year":"2002","journal-title":"Pac Health Dialog"},{"key":"S0022215111001691_ref9","DOI":"10.1097\/MLG.0b013e318039b30f","doi-asserted-by":"publisher"},{"key":"S0022215111001691_ref14","DOI":"10.1001\/archotol.133.10.1002","doi-asserted-by":"publisher"},{"key":"S0022215111001691_ref8","DOI":"10.1288\/00005537-199108000-00004","doi-asserted-by":"publisher"},{"key":"S0022215111001691_ref13","author":"Salit","volume":"132","first-page":"381","year":"1985","journal-title":"Can Med Assoc J"},{"key":"S0022215111001691_ref7","DOI":"10.1017\/S0022215110000691","doi-asserted-by":"publisher"},{"key":"S0022215111001691_ref12","DOI":"10.1007\/s00405-007-0416-8","doi-asserted-by":"publisher"},{"key":"S0022215111001691_ref6","DOI":"10.1097\/MAO.0b013e31805153bd","doi-asserted-by":"publisher"},{"key":"S0022215111001691_ref11","DOI":"10.1016\/j.otc.2008.01.004","doi-asserted-by":"publisher"},{"key":"S0022215111001691_ref5","DOI":"10.2500\/ajr.2007.21.3033","doi-asserted-by":"publisher"},{"key":"S0022215111001691_ref10","DOI":"10.1016\/S1473-3099(03)00858-2","doi-asserted-by":"publisher"},{"key":"S0022215111001691_ref4","author":"Chang","volume":"24","first-page":"1310","year":"2003","journal-title":"Am J Neuroradiol"},{"key":"S0022215111001691_ref3","DOI":"10.1055\/s-0028-1115325","doi-asserted-by":"publisher"},{"key":"S0022215111001691_ref2","DOI":"10.1016\/S0196-0709(80)80016-0","doi-asserted-by":"publisher"},{"key":"S0022215111001691_ref1","DOI":"10.1288\/00005537-196808000-00002","doi-asserted-by":"publisher"},{"key":"S0022215111001691_ref22","author":"Slattery","volume":"29","first-page":"795","year":"1996","journal-title":"Otolaryngol Clin North Am"},{"key":"S0022215111001691_ref21","DOI":"10.1097\/00005537-199603000-00018","doi-asserted-by":"publisher"},{"key":"S0022215111001691_ref18","DOI":"10.1016\/j.crad.2006.01.010","doi-asserted-by":"publisher"}],"container-title":"The Journal of Laryngology & Otology","original-title":[],"language":"en","link":[{"URL":"https:\/\/www.cambridge.org\/core\/services\/aop-cambridge-core\/content\/view\/S0022215111001691","content-type":"unspecified","content-version":"vor","intended-application":"similarity-checking"}],"deposited":{"date-parts":[[2017,6,20]],"date-time":"2017-06-20T04:46:17Z","timestamp":1497933977000},"score":1.0,"subtitle":[],"short-title":[],"issued":{"date-parts":[[2011,8,16]]},"references-count":22,"journal-issue":{"published-print":{"date-parts":[[2011,11]]},"issue":"11"},"alternative-id":["S0022215111001691"],"URL":"http:\/\/dx.doi.org\/10.1017\/s0022215111001691","relation":{"cites":[]},"ISSN":["0022-2151","1748-5460"],"container-title-short":"J. Laryngol. Otol."}