{"indexed":{"date-parts":[[2018,5,2]],"date-time":"2018-05-02T23:52:01Z","timestamp":1525305121625},"reference-count":0,"publisher":"Informa Healthcare","isbn-type":[{"value":"9780849318504","type":"print"},{"value":"9780203488393","type":"electronic"}],"content-domain":{"domain":[],"crossmark-restriction":false},"published-print":{"date-parts":[[2003,6,27]]},"DOI":"10.1201\/9780203488393.ch10","type":"chapter","created":{"date-parts":[[2010,2,23]],"date-time":"2010-02-23T13:35:53Z","timestamp":1266932153000},"source":"Crossref","is-referenced-by-count":0,"title":"Mexico","prefix":"10.1201","member":"301","published-online":{"date-parts":[[2009,12,17]]},"container-title":"International Labeling Requirements for Medical Devices, Medical Equipment and Diagnostic Products","original-title":[],"link":[{"URL":"http:\/\/www.crcnetbase.com\/doi\/pdf\/10.1201\/9780203488393.ch10","content-type":"unspecified","content-version":"vor","intended-application":"similarity-checking"}],"deposited":{"date-parts":[[2016,9,7]],"date-time":"2016-09-07T19:12:25Z","timestamp":1473275545000},"score":1.0,"subtitle":[],"short-title":[],"issued":{"date-parts":[[2003,6,27]]},"ISBN":["9780849318504","9780203488393"],"references-count":0,"alternative-id":["10.1201\/9780203488393.ch10","10.1201\/9780203488393"],"URL":"http:\/\/dx.doi.org\/10.1201\/9780203488393.ch10","relation":{}}