{"indexed":{"date-parts":[[2018,5,11]],"date-time":"2018-05-11T15:42:28Z","timestamp":1526053348128},"reference-count":15,"publisher":"S. Karger AG","issue":"1-2","content-domain":{"domain":[],"crossmark-restriction":false},"published-print":{"date-parts":[[2012]]},"DOI":"10.1159\/000339077","type":"article-journal","created":{"date-parts":[[2012,6,21]],"date-time":"2012-06-21T20:27:59Z","timestamp":1340310479000},"page":"40-46","source":"Crossref","is-referenced-by-count":16,"title":"Bioequivalence of Intravenous and Oral Formulations of the Antiepileptic Drug Lacosamide","prefix":"10.1159","volume":"90","author":[{"given":"Willi","family":"Cawello","sequence":"first","affiliation":[]},{"given":"Rainer","family":"Bonn","sequence":"additional","affiliation":[]},{"given":"Hilmar","family":"Boekens","sequence":"additional","affiliation":[]}],"member":"127","reference":[{"key":"sref_1","author":"Wheless JW","volume":"1","first-page":"49","year":"1999","journal-title":"Expert Opin Pharmacother","DOI":"10.1517\/14656566.1.1.49","doi-asserted-by":"crossref"},{"key":"sref_2","DOI":"10.1111\/j.1528-1167.2007.01188.x","doi-asserted-by":"publisher"},{"key":"sref_3","DOI":"10.1111\/j.1528-1167.2009.02496.x","doi-asserted-by":"publisher"},{"key":"sref_4","DOI":"10.1111\/j.1528-1167.2008.01951.x","doi-asserted-by":"publisher"},{"key":"sref_5","author":"Bialer M","volume":"61","first-page":"1","year":"2004","journal-title":"Epilepsy Res","DOI":"10.1016\/j.eplepsyres.2004.07.010","doi-asserted-by":"crossref"},{"key":"sref_6","author":"Horstmann R","volume":"43","first-page":"188","year":"2002","journal-title":"Epilepsia"},{"key":"sref_7","author":"Cawello W","volume":"45","first-page":"307","year":"2004","journal-title":"Epilepsia"},{"key":"sref_9","author":"Bialer M","volume":"51","first-page":"31","year":"2002","journal-title":"Epilepsy Res","DOI":"10.1016\/S0920-1211(02)00106-7","doi-asserted-by":"crossref"},{"key":"sref_10","author":"Bialer M","volume":"73","first-page":"1","year":"2007","journal-title":"Epilepsy Res","DOI":"10.1016\/j.eplepsyres.2006.10.008","doi-asserted-by":"crossref"},{"key":"sref_11","author":"Beyreuther B","volume":"13","first-page":"22","year":"2007","journal-title":"CNS Drug Rev","DOI":"10.1111\/j.1527-3458.2007.00001.x","doi-asserted-by":"crossref"},{"key":"sref_12","DOI":"10.1177\/0091270009347675","doi-asserted-by":"publisher"},{"key":"sref_13","author":"Moddel G","volume":"80","first-page":"689","year":"2009","journal-title":"J Neurol Neurosurg Psychiatry","DOI":"10.1136\/jnnp.2008.145458","doi-asserted-by":"crossref"},{"key":"sref_15","author":"Nickel B","volume":"48","first-page":"1099","year":"2008","journal-title":"J Clin Pharmacol"},{"key":"sref_16","author":"Biton V","volume":"49","first-page":"418","year":"2008","journal-title":"Epilepsia","DOI":"10.1111\/j.1528-1167.2007.01317.x","doi-asserted-by":"crossref"},{"key":"sref_17","author":"Krauss G","volume":"51","first-page":"951","year":"2010","journal-title":"Epilepsia","DOI":"10.1111\/j.1528-1167.2009.02463.x","doi-asserted-by":"crossref"}],"container-title":"Pharmacology","original-title":[],"language":"en","link":[{"URL":"http:\/\/www.karger.com\/Article\/Pdf\/339077","content-type":"unspecified","content-version":"vor","intended-application":"similarity-checking"}],"deposited":{"date-parts":[[2017,10,25]],"date-time":"2017-10-25T20:43:53Z","timestamp":1508964233000},"score":1.0,"subtitle":[],"short-title":[],"issued":{"date-parts":[[2012]]},"references-count":15,"journal-issue":{"published-print":{"date-parts":[[2012]]},"issue":"1-2"},"URL":"http:\/\/dx.doi.org\/10.1159\/000339077","relation":{"cites":[]},"ISSN":["1423-0313","0031-7012"],"container-title-short":"Pharmacology"}