{"indexed":{"date-parts":[[2018,5,3]],"date-time":"2018-05-03T06:46:50Z","timestamp":1525330010294},"reference-count":33,"publisher":"American Physical Society (APS)","issue":"10","license":[{"URL":"http:\/\/link.aps.org\/licenses\/aps-default-license","start":{"date-parts":[[1975,11,15]],"date-time":"1975-11-15T00:00:00Z","timestamp":185241600000},"delay-in-days":0,"content-version":"vor"}],"content-domain":{"domain":[],"crossmark-restriction":false},"DOI":"10.1103\/physrevb.12.4577","type":"article-journal","created":{"date-parts":[[2002,7,27]],"date-time":"2002-07-27T03:06:47Z","timestamp":1027739207000},"page":"4577-4580","source":"Crossref","is-referenced-by-count":4,"title":"Difference between zero- and first-sound propagation in solid Kr","prefix":"10.1103","volume":"12","author":[{"given":"V. V.","family":"Goldman","sequence":"first","affiliation":[]},{"given":"Michael L.","family":"Klein","sequence":"additional","affiliation":[]}],"member":"16","published-online":{"date-parts":[[1975,11,15]]},"reference":[{"key":"PhysRevB.12.4577Cc1R1","author":"H. J. Maris","volume":"16","first-page":"1331","year":"1967","journal-title":"Philos. Mag.","DOI":"10.1080\/14786436708229745","doi-asserted-by":"crossref"},{"key":"PhysRevB.12.4577Cc2R1","author":"R. A. Cowley","volume":"90","first-page":"1127","year":"1967","journal-title":"Proc. Phys. Soc. Lond.","DOI":"10.1088\/0370-1328\/90\/4\/323","doi-asserted-by":"crossref"},{"key":"PhysRevB.12.4577Cc3R1","author":"E. C. Svennson","volume":"165","first-page":"1063","year":"1968","journal-title":"Phys. Rev.","DOI":"10.1103\/PhysRev.165.1063","doi-asserted-by":"crossref"},{"key":"PhysRevB.12.4577Cc4R1","author":"J. S. Blinick","volume":"2","first-page":"2139","year":"1970","journal-title":"Phys. Rev. B","DOI":"10.1103\/PhysRevB.2.2139","doi-asserted-by":"crossref"},{"key":"PhysRevB.12.4577Cc5R1","author":"H. E. Jackson","volume":"31","first-page":"296","year":"1973","journal-title":"Phys. Rev. Lett.","DOI":"10.1103\/PhysRevLett.31.296","doi-asserted-by":"crossref"},{"key":"PhysRevB.12.4577Cc6R1","author":"J. Skalyo, Jr.","volume":"7","first-page":"4670","year":"1973","journal-title":"Phys. Rev. B","DOI":"10.1103\/PhysRevB.7.4670","doi-asserted-by":"crossref"},{"key":"PhysRevB.12.4577Cc7R1","author":"V. V. Goldman","volume":"4","first-page":"567","year":"1971","journal-title":"Phys. Rev. B","DOI":"10.1103\/PhysRevB.4.567","doi-asserted-by":"crossref"},{"key":"PhysRevB.12.4577Cc8R1","author":"G. Niklason","volume":"14","first-page":"138","year":"1972","journal-title":"Phys. Kondens. Mater."},{"key":"PhysRevB.12.4577Cc9R1","author":"M. V. Bobetic","volume":"2","first-page":"4169","year":"1972","journal-title":"Phys. Rev. B","DOI":"10.1103\/PhysRevB.2.4169","doi-asserted-by":"crossref"},{"key":"PhysRevB.12.4577Cc10R1","author":"M. L. Klein","volume":"7","first-page":"1571","year":"1973","journal-title":"Phys. Rev. B","DOI":"10.1103\/PhysRevB.7.1571","doi-asserted-by":"crossref"},{"key":"PhysRevB.12.4577Cc11R1","author":"M. L. Klein","volume":"6","first-page":"2433","year":"1972","journal-title":"Phys. Rev. B","DOI":"10.1103\/PhysRevB.6.2433","doi-asserted-by":"crossref"},{"key":"PhysRevB.12.4577Cc12R1","author":"M. Cavallini","volume":"42","first-page":"136","year":"1971","journal-title":"Entropie"},{"key":"PhysRevB.12.4577Cc13R1","author":"J. A. Barker","volume":"61","first-page":"3081","year":"1974","journal-title":"J. Chem. Phys.","DOI":"10.1063\/1.1682464","doi-asserted-by":"crossref"},{"key":"PhysRevB.12.4577Cc14R1","author":"U. Buck","volume":"8","first-page":"2409","year":"1973","journal-title":"Phys. Rev. A","DOI":"10.1103\/PhysRevA.8.2409","doi-asserted-by":"crossref"},{"key":"PhysRevB.12.4577Cc15R1","author":"R. Aziz","journal-title":"Mol. Phys."},{"key":"PhysRevB.12.4577Cc17R1","author":"J. Skalyo, Jr.","volume":"9","first-page":"1797","year":"1974","journal-title":"Phys. Rev. B","DOI":"10.1103\/PhysRevB.9.1797","doi-asserted-by":"crossref"},{"key":"PhysRevB.12.4577Cc18R1","author":"M. L. Klein","volume":"2","first-page":"4995","year":"1970","journal-title":"Phys. Rev. B","DOI":"10.1103\/PhysRevB.2.4995","doi-asserted-by":"crossref"},{"key":"PhysRevB.12.4577Cc19R1","author":"H. Horner","volume":"205","first-page":"72","year":"1967","journal-title":"Z. Phys.","DOI":"10.1007\/BF01326300","doi-asserted-by":"crossref"},{"key":"PhysRevB.12.4577Cc20R1","author":"W. G\u00f6tze","volume":"217","first-page":"170","year":"1968","journal-title":"Z. Phys.","DOI":"10.1007\/BF01390505","doi-asserted-by":"crossref"},{"key":"PhysRevB.12.4577Cc21R1","author":"M. L. Klein","volume":"4","first-page":"537","year":"1971","journal-title":"Phys. Rev. B","DOI":"10.1103\/PhysRevB.4.537","doi-asserted-by":"crossref"},{"key":"PhysRevB.12.4577Cc22R1","author":"M. L. Klein","volume":"6","first-page":"2433","year":"1972","journal-title":"Phys. Rev. B","DOI":"10.1103\/PhysRevB.6.2433","doi-asserted-by":"crossref"},{"key":"PhysRevB.12.4577Cc23R1","author":"T. R. Koehler","volume":"22","first-page":"777","year":"1969","journal-title":"Phys. Rev. Lett.","DOI":"10.1103\/PhysRevLett.22.777","doi-asserted-by":"crossref"},{"key":"PhysRevB.12.4577Cc24R1","author":"V. V. Goldman","volume":"24","first-page":"1424","year":"1970","journal-title":"Phys. Rev. Lett.","DOI":"10.1103\/PhysRevLett.24.1424","doi-asserted-by":"crossref"},{"key":"PhysRevB.12.4577Cc25R1","author":"H. Peter","volume":"34","first-page":"255","year":"1973","journal-title":"J. Phys. Chem. Solids","DOI":"10.1016\/0022-3697(73)90085-1","doi-asserted-by":"crossref"},{"key":"PhysRevB.12.4577Cc26R1","author":"H. Horner","volume":"9","first-page":"79","year":"1971","journal-title":"Solid State Commun.","DOI":"10.1016\/0038-1098(71)90059-7","doi-asserted-by":"crossref"},{"key":"PhysRevB.12.4577Cc26R2","author":"H. Horner","year":"1974","volume-title":"Dynamical Properties of Solids"},{"key":"PhysRevB.12.4577Cc28R1","author":"J. P. Hansen","volume":"35","first-page":"L","year":"1974","journal-title":"J. Phys. Lett.","DOI":"10.1051\/jphyslet:0197400350302900","doi-asserted-by":"crossref"},{"key":"PhysRevB.12.4577Cc29R1","author":"S. Gewurtz","volume":"10","first-page":"3487","year":"1974","journal-title":"Phys. Rev. B","DOI":"10.1103\/PhysRevB.10.3487","doi-asserted-by":"crossref"},{"key":"PhysRevB.12.4577Cc30R1","author":"Y. Fujii","volume":"10","first-page":"3647","year":"1974","journal-title":"Phys. Rev. B","DOI":"10.1103\/PhysRevB.10.3647","doi-asserted-by":"crossref"},{"key":"PhysRevB.12.4577Cc31R1","author":"R. A. McLaren","volume":"11","first-page":"1705","year":"1975","journal-title":"Phys. Rev. B","DOI":"10.1103\/PhysRevB.11.1705","doi-asserted-by":"crossref"},{"key":"PhysRevB.12.4577Cc32R1","author":"Y. Endoh","volume":"11","first-page":"1681","year":"1975","journal-title":"Phys. Rev. B","DOI":"10.1103\/PhysRevB.11.1681","doi-asserted-by":"crossref"},{"key":"PhysRevB.12.4577Cc33R1","author":"N. S. Gornall","volume":"4","first-page":"4518","year":"1971","journal-title":"Phys. Rev. B","DOI":"10.1103\/PhysRevB.4.4518","doi-asserted-by":"crossref"},{"key":"PhysRevB.12.4577Cc34R1","author":"N. A. Lurie","volume":"9","first-page":"2661","year":"1974","journal-title":"Phys. Rev. B","DOI":"10.1103\/PhysRevB.9.2661","doi-asserted-by":"crossref"}],"container-title":"Physical Review B","original-title":[],"language":"en","link":[{"URL":"http:\/\/link.aps.org\/article\/10.1103\/PhysRevB.12.4577","content-type":"unspecified","content-version":"vor","intended-application":"syndication"},{"URL":"http:\/\/harvest.aps.org\/v2\/journals\/articles\/10.1103\/PhysRevB.12.4577\/fulltext","content-type":"unspecified","content-version":"vor","intended-application":"similarity-checking"}],"deposited":{"date-parts":[[2017,12,10]],"date-time":"2017-12-10T06:21:06Z","timestamp":1512886866000},"score":1.0,"subtitle":[],"short-title":[],"issued":{"date-parts":[[1975,11,15]]},"references-count":33,"journal-issue":{"published-print":{"date-parts":[[1975,11]]},"issue":"10"},"URL":"http:\/\/dx.doi.org\/10.1103\/physrevb.12.4577","relation":{"cites":[]},"ISSN":["0556-2805"],"container-title-short":"Phys. Rev. B"}