{"indexed":{"date-parts":[[2018,5,16]],"date-time":"2018-05-16T19:42:31Z","timestamp":1526499751259},"reference-count":15,"publisher":"Institute of Electrical and Electronics Engineers (IEEE)","issue":"11","content-domain":{"domain":[],"crossmark-restriction":false},"published-print":{"date-parts":[[2005,11]]},"DOI":"10.1109\/jqe.2005.857066","type":"article-journal","created":{"date-parts":[[2005,10,24]],"date-time":"2005-10-24T18:19:15Z","timestamp":1130177955000},"page":"1341-1348","source":"Crossref","is-referenced-by-count":23,"title":"High-performance 640-nm-range GaInP-AlGaInP lasers based on the longitudinal photonic bandgap crystal with narrow vertical beam divergence","prefix":"10.1109","volume":"41","author":[{"given":"M.V.","family":"Maximov","sequence":"first","affiliation":[]},{"given":"Y.M.","family":"Shernyakov","sequence":"additional","affiliation":[]},{"given":"I.I.","family":"Novikov","sequence":"additional","affiliation":[]},{"given":"S.M.","family":"Kuznetsov","sequence":"additional","affiliation":[]},{"given":"L.Ya.","family":"Karachinsky","sequence":"additional","affiliation":[]},{"given":"N.Yu.","family":"Gordeev","sequence":"additional","affiliation":[]},{"given":"V.P.","family":"Kalosha","sequence":"additional","affiliation":[]},{"given":"V.A.","family":"Shchukin","sequence":"additional","affiliation":[]},{"given":"N.N.","family":"Ledentsov","sequence":"additional","affiliation":[]}],"member":"263","container-title":"IEEE Journal of Quantum Electronics","original-title":[],"link":[{"URL":"http:\/\/xplorestaging.ieee.org\/ielx5\/3\/32565\/01522582.pdf?arnumber=1522582","content-type":"unspecified","content-version":"vor","intended-application":"similarity-checking"}],"deposited":{"date-parts":[[2017,11,13]],"date-time":"2017-11-13T23:02:32Z","timestamp":1510614152000},"score":1.0,"subtitle":[],"short-title":[],"issued":{"date-parts":[[2005,11]]},"references-count":15,"journal-issue":{"issue":"11"},"URL":"http:\/\/dx.doi.org\/10.1109\/jqe.2005.857066","relation":{},"ISSN":["0018-9197"],"container-title-short":"IEEE J. Quantum Electron."}