{"indexed":{"date-parts":[[2018,4,30]],"date-time":"2018-04-30T17:42:25Z","timestamp":1525110145696},"reference-count":7,"publisher":"Ovid Technologies (Wolters Kluwer Health)","issue":"3","content-domain":{"domain":[],"crossmark-restriction":false},"published-print":{"date-parts":[[2018]]},"DOI":"10.1097\/01.nep.0000000000000238","type":"article-journal","created":{"date-parts":[[2018,3,4]],"date-time":"2018-03-04T19:43:12Z","timestamp":1520192592000},"page":"175-177","source":"Crossref","is-referenced-by-count":0,"title":"Value Affordances in Students\u2019 Probability of Persisting as a Nursing Major","prefix":"10.1097","volume":"39","author":[{"given":"Meghan I.H.","family":"Lindeman","sequence":"first","affiliation":[]},{"given":"Amanda M.","family":"Durik","sequence":"additional","affiliation":[]}],"member":"276","container-title":"Nursing Education Perspectives","original-title":[],"language":"en","link":[{"URL":"http:\/\/Insights.ovid.com\/crossref?an=00024776-201805000-00013","content-type":"unspecified","content-version":"vor","intended-application":"similarity-checking"}],"deposited":{"date-parts":[[2018,4,27]],"date-time":"2018-04-27T16:40:14Z","timestamp":1524847214000},"score":1.0,"subtitle":[""],"short-title":[],"issued":{"date-parts":[[2018]]},"references-count":7,"journal-issue":{"issue":"3"},"URL":"http:\/\/dx.doi.org\/10.1097\/01.nep.0000000000000238","relation":{},"ISSN":["1536-5026"],"container-title-short":"Nursing Education Perspectives"}