{"indexed":{"date-parts":[[2018,5,8]],"date-time":"2018-05-08T01:52:21Z","timestamp":1525744341121},"publisher-location":"Reston, Virigina","reference-count":49,"publisher":"American Institute of Aeronautics and Astronautics","isbn-type":[{"value":"9781624101281","type":"electronic"}],"content-domain":{"domain":["arc.aiaa.org"],"crossmark-restriction":true},"published-print":{"date-parts":[[2008,1,7]]},"DOI":"10.2514\/6.2008-518","type":"paper-conference","created":{"date-parts":[[2013,11,5]],"date-time":"2013-11-05T21:41:56Z","timestamp":1383687716000},"update-policy":"http:\/\/dx.doi.org\/10.2514\/aiaa_crossmarkpolicy","source":"Crossref","is-referenced-by-count":5,"title":"Multifidelity Approaches for the Computational Analysis and Design of Effective Flapping Wing Vehicles","prefix":"10.2514","author":[{"given":"David","family":"Willis","sequence":"first","affiliation":[]},{"given":"Per Olof","family":"Persson","sequence":"additional","affiliation":[]},{"given":"Emily","family":"Israeli","sequence":"additional","affiliation":[]},{"given":"Jaime","family":"Peraire","sequence":"additional","affiliation":[]},{"given":"Sharon","family":"Swartz","sequence":"additional","affiliation":[]},{"given":"Kenneth","family":"Breuer","sequence":"additional","affiliation":[]}],"member":"1387","published-online":{"date-parts":[[2012,6,19]]},"reference":[{"key":"p_1","unstructured":"1Hall, K. C., and Hall, S. R., Minimum induced power requirements for flapping flight Journal of Fluid Mechanics, 1996, Vol.323, pp.285-315.","DOI":"10.1017\/S0022112096000924","doi-asserted-by":"crossref"},{"issue":"3","key":"p_2","first-page":"352","volume":"35","author":"Hall K. C.","year":"1998","journal-title":"Power Requirements for Large-Amplitude Flapping Flight Journal of Aircraft"},{"key":"p_3","author":"Hall K. C.","year":"1997","volume-title":"35th Aerospace Sciences Meeting and Exhibit"},{"key":"p_4","author":"Willis J.","year":"2006","volume-title":"AIAA-2006-2994"},{"key":"p_5","author":"Willis E.R.","year":"2007","volume-title":"AIAA Conference, AIAA-2007-3803"},{"key":"p_7","DOI":"10.2514\/6.2005-854","doi-asserted-by":"publisher"},{"key":"p_8","author":"Willis J.","year":"2006","volume-title":"44th AIAA Aerospace Sciences Meeting, AIAA-2006-1253"},{"key":"p_9","DOI":"10.2514\/6.2007-42","doi-asserted-by":"publisher"},{"key":"p_10","author":"Peraire J.","volume":"26","first-page":"2135","year":"1988","journal-title":"Engn."},{"key":"p_11","author":"Jameson","first-page":"361","year":"1989","volume-title":"Vol 245 no. 4916"},{"key":"p_12","author":"Katz A.","year":"2001","volume-title":"Cambridge University Press"},{"key":"p_13","author":"Newman","first-page":"20","year":"1985","journal-title":"J. Eng. Math."},{"key":"p_14","DOI":"10.1016\/0045-7825(74)90009-7","doi-asserted-by":"publisher"},{"key":"p_15","author":"Morino C.C.","volume":"12","first-page":"191","journal-title":"AIAA J."},{"key":"p_16","author":"Willis J.","year":"2007","volume-title":"AIAA Conference, AIAA-2007-4182"},{"key":"p_17","DOI":"10.1002\/fld.1240","doi-asserted-by":"publisher"},{"key":"p_18","DOI":"10.2514\/6.2005-854","doi-asserted-by":"publisher"},{"key":"p_19","author":"Vest M.","year":"1999","volume-title":"AIAA 37th Aerospace Sciences Meeting in Reno, NV"},{"key":"p_21","DOI":"10.2514\/3.13067","doi-asserted-by":"publisher"},{"key":"p_24","unstructured":"24D.J.Willis,An Unsteady, Accelerated, High Order Panel Method with Vortex Particle Wakes, MIT PhD. Thesis,2006."},{"key":"p_25","author":"Winter Y.","first-page":"434","year":"1998","journal-title":"Journal of Comparative Physiology B-Biochemical Systemic and Environmental Physiology","DOI":"10.1007\/s003600050163","doi-asserted-by":"crossref"},{"key":"p_26","author":"Winter Y.","first-page":"105","year":"1998","journal-title":"Journal of Comparative Physiology B-Biochemical Systemic and Environmental Physiology","DOI":"10.1007\/s003600050126","doi-asserted-by":"crossref"},{"key":"p_27","author":"Voigt C.C.","first-page":"38","year":"1999","journal-title":"Journal of Comparative Physiology B-Biochemical Systemic and Environmental Physiology","DOI":"10.1007\/s003600050191","doi-asserted-by":"crossref"},{"key":"p_29","author":"Toomey J. D.","year":"2006","volume-title":"AIAA 2006-3211, 36th AIAA Fluid Dynamics Conference and Exhibit"},{"key":"p_30","author":"Jones T.C.","volume":"195","first-page":"307","year":"2001","volume-title":"AIAA Progress in Astronautics and Aeronautics"},{"key":"p_31","DOI":"10.4271\/2004-01-3138","doi-asserted-by":"publisher"},{"key":"p_32","author":"Viieru J.","year":"2006","volume-title":"44th AIAA Aerospace Sciences Meeting and Exhibit"},{"key":"p_33","author":"Abdulrahim R.","year":"2004","volume-title":"Navigation and Control Conference"},{"key":"p_35","author":"Rodden","year":"1997","volume-title":"International Forum on Aeroelasticity and Structural Dynamics"},{"key":"p_36","author":"Brebbia","year":"1984","volume-title":"Theory and Applications in Engineering"},{"key":"p_37","DOI":"10.1146\/annurev.fl.17.010185.002515","doi-asserted-by":"publisher"},{"key":"p_38","DOI":"10.1006\/jcph.1997.5667","doi-asserted-by":"publisher"},{"key":"p_39","author":"Rehbach","year":"1977","volume-title":"pp, 289-298"},{"key":"p_40","author":"Philips J.K.","volume":"16","year":"1997","journal-title":"IEEE Transactions on Computer Aided Design of Integrated Curcuits and Systems, IEEE"},{"key":"p_41","author":"Barnes P.","year":"1986","volume-title":"December"},{"key":"p_42","author":"Greegard V.","volume":"73","first-page":"325","year":"1987","journal-title":"Phys."},{"key":"p_43","author":"Saad M.","year":"1986","volume-title":"GMRES: A generalized Minimal Residual Algorithm for Solving Non-Symmetric Linear Systems"},{"key":"p_44","DOI":"10.1146\/annurev.fluid.37.061903.175743","doi-asserted-by":"publisher"},{"key":"p_45","author":"Lai C.S.","volume":"160","first-page":"705","year":"2000","journal-title":"Phys."},{"key":"p_48","author":"Graham K.","volume":"425","first-page":"707","year":"2003","journal-title":"Nature","DOI":"10.1038\/nature02000","doi-asserted-by":"crossref"},{"key":"p_49","DOI":"10.1023\/A:1012873910884","doi-asserted-by":"publisher"},{"key":"p_50","author":"Peraire P.-O.","series-title":"SIAM J. Sci. Comput., (2008), to appear.","volume-title":"The compact discontinuous Galerkin (CDG) method for elliptic problems"},{"key":"p_51","author":"Persson J.","series-title":"SIAM J. Sci. Comput., (2008), to appear.","volume-title":"Newton-GMRES preconditioning for discontinuous Galerkin discretizations of the Navier-Stokes equations"},{"key":"p_52","author":"Persson J.","first-page":"2007","year":"2007","volume-title":"45th AIAA Aerospace Sciences Meeting and Exhibit"},{"key":"p_53","author":"Persson J.","first-page":"2007","year":"2007","volume-title":"18th AIAA Computational Fluid Dynamics Conference"},{"key":"p_54","DOI":"10.1088\/1748-3182\/1\/4\/S02","doi-asserted-by":"publisher"},{"key":"p_55","DOI":"10.1146\/annurev.fl.15.010183.001255","doi-asserted-by":"publisher"},{"key":"p_56","author":"Katz S.","year":"1996","volume-title":"AIAA Joural, Vol 34., No."},{"key":"p_61","author":"Figure","volume-title":"\u201cbubble"}],"event":"46th AIAA Aerospace Sciences Meeting and Exhibit","container-title":"46th AIAA Aerospace Sciences Meeting and Exhibit","original-title":[],"link":[{"URL":"http:\/\/arc.aiaa.org\/doi\/pdf\/10.2514\/6.2008-518","content-type":"unspecified","content-version":"vor","intended-application":"similarity-checking"}],"deposited":{"date-parts":[[2017,6,22]],"date-time":"2017-06-22T01:27:37Z","timestamp":1498094857000},"score":1.0,"subtitle":[],"short-title":[],"issued":{"date-parts":[[2008,1,7]]},"ISBN":["9781624101281"],"references-count":49,"alternative-id":["10.2514\/6.2008-518","10.2514\/MASM08"],"URL":"http:\/\/dx.doi.org\/10.2514\/6.2008-518","relation":{"cites":[]}}